yeaudio/__init__.py
yeaudio/audio.py
yeaudio/augmentation.py
yeaudio/vad_model.py
yeaudio/utils/__init__.py
yeaudio/utils/av_utils.py
yeaudio/utils/e2e_vad.py
yeaudio/utils/frontend.py
yeaudio/utils/utils.py
yeaudio/utils/vad_models/am.mvn
yeaudio/utils/vad_models/config.yaml
yeaudio/utils/vad_models/model.onnx
yeaudio/utils/vad_models/model_quant.onnx
yeaudio-0.0.8.dist-info/LICENSE
yeaudio-0.0.8.dist-info/METADATA
yeaudio-0.0.8.dist-info/WHEEL
yeaudio-0.0.8.dist-info/top_level.txt
yeaudio-0.0.8.dist-info/RECORD
