Metadata-Version: 2.2
Name: yeaudio
Version: 0.0.8
Summary: Audio ToolKit for Python
Home-page: https://github.com/yeyupiaoling/YeAudio
Download-URL: https://github.com/yeyupiaoling/YeAudio.git
Author: yeyupiaoling
License: Apache License 2.0
Keywords: audio,speech
Classifier: Intended Audience :: Developers
Classifier: License :: OSI Approved :: Apache Software License
Classifier: Operating System :: OS Independent
Classifier: Natural Language :: Chinese (Simplified)
Classifier: Programming Language :: Python :: 3
Classifier: Programming Language :: Python :: 3.7
Classifier: Programming Language :: Python :: 3.8
Classifier: Programming Language :: Python :: 3.9
Classifier: Programming Language :: Python :: 3.10
Classifier: Programming Language :: Python :: 3.11
Classifier: Programming Language :: Python :: 3.12
Classifier: Topic :: Utilities
License-File: LICENSE
Requires-Dist: numpy>=1.19.2
Requires-Dist: resampy>=0.2.2
Requires-Dist: soundfile>=0.12.1
Requires-Dist: av>=10.0.0
Requires-Dist: scipy>=1.6.3
Requires-Dist: pillow>=10.0.1
Requires-Dist: loguru>=0.7.2
Requires-Dist: kaldi-native-fbank
Dynamic: author
Dynamic: classifier
Dynamic: description
Dynamic: description-content-type
Dynamic: download-url
Dynamic: home-page
Dynamic: keywords
Dynamic: license
Dynamic: requires-dist
Dynamic: summary
